MANIFEST.in
README.md
setup.py
django_scaffold_toolkit.egg-info/PKG-INFO
django_scaffold_toolkit.egg-info/SOURCES.txt
django_scaffold_toolkit.egg-info/dependency_links.txt
django_scaffold_toolkit.egg-info/top_level.txt
scaffold_toolkit/__init__.py
scaffold_toolkit/admin.py
scaffold_toolkit/bootstrap.py
scaffold_toolkit/fields.py
scaffold_toolkit/models.py
scaffold_toolkit/tests.py
scaffold_toolkit/urls.py
scaffold_toolkit/views.py
scaffold_toolkit/backends/__init__.py
scaffold_toolkit/backends/mailgun.py
scaffold_toolkit/backends/modelemailbackend.py
scaffold_toolkit/forms/__init__.py
scaffold_toolkit/forms/datetimepicker.py
scaffold_toolkit/forms/kindeditor.py
scaffold_toolkit/forms/tagfield.py
scaffold_toolkit/forms/umeditor.py
scaffold_toolkit/formvalidator/__init__.py
scaffold_toolkit/formvalidator/forms/__init__.py
scaffold_toolkit/formvalidator/forms/validators.py
scaffold_toolkit/formvalidator/static/formvalidator/formValidator.js
scaffold_toolkit/formvalidator/static/formvalidator/css/formValidation.min.css
scaffold_toolkit/formvalidator/static/formvalidator/js/formValidation.min.js
scaffold_toolkit/formvalidator/static/formvalidator/js/framework/bootstrap.min.js
scaffold_toolkit/formvalidator/static/formvalidator/js/framework/foundation.min.js
scaffold_toolkit/formvalidator/static/formvalidator/js/framework/pure.min.js
scaffold_toolkit/formvalidator/static/formvalidator/js/framework/semantic.min.js
scaffold_toolkit/formvalidator/static/formvalidator/js/framework/uikit.min.js
scaffold_toolkit/formvalidator/static/formvalidator/js/language/ar_MA.js
scaffold_toolkit/formvalidator/static/formvalidator/js/language/be_FR.js
scaffold_toolkit/formvalidator/static/formvalidator/js/language/be_NL.js
scaffold_toolkit/formvalidator/static/formvalidator/js/language/bg_BG.js
scaffold_toolkit/formvalidator/static/formvalidator/js/language/ca_ES.js
scaffold_toolkit/formvalidator/static/formvalidator/js/language/cs_CZ.js
scaffold_toolkit/formvalidator/static/formvalidator/js/language/da_DK.js
scaffold_toolkit/formvalidator/static/formvalidator/js/language/de_DE.js
scaffold_toolkit/formvalidator/static/formvalidator/js/language/en_US.js
