Metadata-Version: 1.1
Name: django-scaffold-toolkit
Version: 0.3.0
Summary: Django开发中一组常用工具。包括表单生成，验证，富文本编辑器，useragent检测等等
Home-page: https://github.com/yuanxu/django-scaffold
Author: YuanXu
Author-email: ankh2008@gmail.com
License: LICENSE.txt
Platform: UNKNOWN
Classifier: Development Status :: 3 - Alpha
Classifier: Intended Audience :: Developers
Classifier: License :: OSI Approved :: Apache Software License
Classifier: Programming Language :: Python :: 2
Classifier: Programming Language :: Python :: 2.7
Classifier: Programming Language :: Python :: 3
Classifier: Programming Language :: Python :: 3.4
Classifier: Operating System :: OS Independent
Classifier: Topic :: Software Development :: Libraries
Classifier: Topic :: Utilities
Classifier: Environment :: Web Environment
Classifier: Framework :: Django
